smashsend/__init__.py
smashsend/client.py
smashsend/errors.py
smashsend/api/contacts.py
smashsend/api/emails.py
smashsend/api/webhooks.py
smashsend/interfaces/types.py
smashsend/utils/http_client.py
smashsend-0.1.0.dist-info/METADATA
smashsend-0.1.0.dist-info/WHEEL
smashsend-0.1.0.dist-info/licenses/LICENSE
smashsend-0.1.0.dist-info/RECORD
