Metadata-Version: 2.4
Name: smashsend
Version: 0.1.0
Summary: SmashSend Python SDK - Official Python client for SmashSend API
Project-URL: Homepage, https://smashsend.com
Project-URL: Repository, https://github.com/smashsend/smashsend-python
Project-URL: Issues, https://github.com/smashsend/smashsend-python/issues
Author: SmashSend
License-Expression: MIT
License-File: LICENSE
Classifier: License :: OSI Approved :: MIT License
Classifier: Operating System :: OS Independent
Classifier: Programming Language :: Python :: 3
Requires-Python: >=3.8
Requires-Dist: pydantic>=2.0.0
Requires-Dist: requests>=2.31.0
Provides-Extra: dev
Requires-Dist: black>=23.0.0; extra == 'dev'
Requires-Dist: flake8>=6.0.0; extra == 'dev'
Requires-Dist: isort>=5.0.0; extra == 'dev'
Requires-Dist: mypy>=1.0.0; extra == 'dev'
Requires-Dist: pytest-cov>=4.0.0; extra == 'dev'
Requires-Dist: pytest>=7.0.0; extra == 'dev'
